mdquantumlite/__init__.py
mdquantumlite/mdquantum_lite.py
mdquantumlite/quantum_feature.py
mdquantumlite2-0.1.0.dist-info/licenses/LICENSE
mdquantumlite2-0.1.0.dist-info/METADATA
mdquantumlite2-0.1.0.dist-info/WHEEL
mdquantumlite2-0.1.0.dist-info/top_level.txt
mdquantumlite2-0.1.0.dist-info/RECORD
