Metadata-Version: 2.4
Name: mdquantumlite2
Version: 0.1.0
Summary: A lightweight quantum-enhanced regression model based on LightGBM
Home-page: https://github.com/Parham-Dehghan/MD_library
Author: Parham Dehghan
Author-email: dehghanparham6@gmail.com
Classifier: Programming Language :: Python :: 3
Classifier: Programming Language :: Python :: 3.8
Classifier: Programming Language :: Python :: 3.9
Classifier: Programming Language :: Python :: 3.10
Classifier: Programming Language :: Python :: 3.11
Classifier: Programming Language :: Python :: 3.12
Classifier: License :: OSI Approved :: MIT License
Classifier: Operating System :: OS Independent
Requires-Python: >=3.8
License-File: LICENSE
Requires-Dist: numpy>=1.20
Requires-Dist: pandas>=1.3
Requires-Dist: scikit-learn>=1.0
Requires-Dist: scipy>=1.7
Requires-Dist: lightgbm>=3.0
Provides-Extra: quantum
Requires-Dist: pennylane>=0.20; extra == "quantum"
Dynamic: author
Dynamic: author-email
Dynamic: classifier
Dynamic: description
Dynamic: description-content-type
Dynamic: home-page
Dynamic: license-file
Dynamic: provides-extra
Dynamic: requires-dist
Dynamic: requires-python
Dynamic: summary
